ai_snake/__init__.py
ai_snake/interpreter.py
ai_snake/parser.py
AiSnake-0.1.2.dist-info/LICENSE
AiSnake-0.1.2.dist-info/METADATA
AiSnake-0.1.2.dist-info/WHEEL
AiSnake-0.1.2.dist-info/entry_points.txt
AiSnake-0.1.2.dist-info/top_level.txt
AiSnake-0.1.2.dist-info/RECORD
