Metadata-Version: 2.1
Name: AiSnake
Version: 0.1.2
Summary: A beginner-friendly programming language focused on AI.
Home-page: https://github.com/yourusername/AiSnake
Author: K. Mohammed Imran
Author-email: your_email@example.com
License: UNKNOWN
Platform: UNKNOWN
License-File: LICENSE
Requires-Dist: scikit-learn
Requires-Dist: numpy
Requires-Dist: joblib
